verdoc.py
verdoc-1.0.2.dist-info/LICENSE
verdoc-1.0.2.dist-info/METADATA
verdoc-1.0.2.dist-info/WHEEL
verdoc-1.0.2.dist-info/entry_points.txt
verdoc-1.0.2.dist-info/top_level.txt
verdoc-1.0.2.dist-info/RECORD
