Metadata-Version: 2.1
Name: verdoc
Version: 1.0.2
Summary: Deploy references from source control.
Home-page: https://pypi.org/project/verdoc
Author: David Tucker
Author-email: david@tucker.name
License: LGPLv2+
Project-URL: Code, https://github.com/dmtucker/verdoc
Project-URL: Documentation, https://dmtucker.github.io/verdoc
Project-URL: Issues, https://github.com/dmtucker/verdoc/issues
Platform: UNKNOWN
Classifier: License :: OSI Approved :: GNU Lesser General Public License v2 or later (LGPLv2+)
Classifier: Intended Audience :: End Users/Desktop
Classifier: Programming Language :: Python :: 3.7
Classifier: Programming Language :: Python :: 3.8
Classifier: Programming Language :: Python :: 3.9
Classifier: Development Status :: 4 - Beta
Requires-Python: >= 3.7
License-File: LICENSE
Requires-Dist: click (>=7.0)
Requires-Dist: GitPython (>=3.0)
Requires-Dist: setuptools (>=41.2)
